atx/__init__.py
atx/__main__.py
atx/base.py
atx/comtools.py
atx/consts.py
atx/errors.py
atx/imutils.py
atx/ioskit.py
atx/logutils.py
atx/patch.py
atx/strutils.py
atx/adbkit/__init__.py
atx/adbkit/client.py
atx/adbkit/device.py
atx/adbkit/mixins.py
atx/adbkit/openstf/__init__.py
atx/adbkit/openstf/keycode.py
atx/adbkit/openstf/service.py
atx/adbkit/openstf/stfwire.proto
atx/adbkit/openstf/stfwire_pb2.py
atx/adbkit/openstf/test_service.py
atx/adbkit/openstf/tkinput.py
atx/androaxml/__init__.py
atx/cmds/__init__.py
atx/cmds/doctor.py
atx/cmds/info.py
atx/cmds/install.py
atx/cmds/iosdeveloper.py
atx/cmds/minicap.py
atx/cmds/monkey.py
atx/cmds/record.py
atx/cmds/run.py
atx/cmds/screen.py
atx/cmds/screencap.py
atx/cmds/screenrecord.py
atx/cmds/tcpproxy.py
atx/cmds/tkgui.py
atx/cmds/utils.py
atx/cmds/static/favicon.ico
atx/cmds/static/favicon.png
atx/cmds/static/help.md
atx/cmds/static/index.html
atx/cmds/static/recorder.ico
atx/cmds/static/css/bootstrap-3.3.5.min.css
atx/cmds/static/css/index.css
atx/cmds/static/css/jquery.fancybox.min.css
atx/cmds/static/fonts/glyphicons-halflings-regular.ttf
atx/cmds/static/fonts/glyphicons-halflings-regular.woff
atx/cmds/static/fonts/glyphicons-halflings-regular.woff2
atx/cmds/static/icons/back.ico
atx/cmds/static/icons/exit.ico
atx/cmds/static/icons/home.ico
atx/cmds/static/icons/menu.ico
atx/cmds/static/icons/power.ico
atx/cmds/static/icons/rotate.ico
atx/cmds/static/icons/rotate2.ico
atx/cmds/static/icons/save.ico
atx/cmds/static/icons/volume_down.ico
atx/cmds/static/icons/volume_up.ico
atx/cmds/static/js/bootstrap-3.3.5.min.js
atx/cmds/static/js/index.js
atx/cmds/static/js/jquery-1.11.3.min.js
atx/cmds/static/js/jquery.fancybox.pack.js
atx/cmds/static/js/jquery.mousewheel.min.js
atx/cmds/static/js/notify.js
atx/cmds/static/js/vue.js
atx/cmds/static/js/vue.min.js
atx/drivers/__init__.py
atx/drivers/android.py
atx/drivers/dummy.py
atx-1.2.0.dist-info/DESCRIPTION.rst
atx-1.2.0.dist-info/METADATA
atx-1.2.0.dist-info/RECORD
atx-1.2.0.dist-info/WHEEL
atx-1.2.0.dist-info/metadata.json
atx-1.2.0.dist-info/pbr.json
atx-1.2.0.dist-info/top_level.txt
