Metadata-Version: 2.0
Name: atx
Version: 1.2.0
Summary: Automation test library for android based on opencv
Home-page: https://github.com/codeskyblue/AirtestX
Author: codeskyblue
Author-email: codeskyblue@gmail.com
License: Apache
Platform: UNKNOWN
Classifier: Environment :: Console
Classifier: Intended Audience :: Developers
Classifier: Operating System :: OS Independent
Classifier: Programming Language :: Python :: 2.7
Classifier: Programming Language :: Python :: 3.4
Classifier: Programming Language :: Python :: 3.5
Requires-Dist: aircv (==1.4.6)
Requires-Dist: futures (==3.0.5)
Requires-Dist: tornado (>=4.4)
Requires-Dist: maproxy (==0.0.12)
Requires-Dist: tqdm (==4.5.0)
Requires-Dist: PyYAML (==3.11)
Requires-Dist: numpy (>=1.11.0)
Requires-Dist: Pillow (>=2.7.0)
Requires-Dist: requests (>=2.9.1)
Requires-Dist: facebook-wda (>=0.2.0)
Requires-Dist: imageio (>=1.5)
Requires-Dist: colorama (>=0.3.7)
Requires-Dist: AxmlParserPY (==0.0.3)
Requires-Dist: uiautomator2
Requires-Dist: subprocess32 (==3.2.7); (python_version <= '2.7')
